sckinetics/ODEsolver.py
sckinetics/__init__.py
scKinetics-0.2.2.dist-info/LICENSE
scKinetics-0.2.2.dist-info/METADATA
scKinetics-0.2.2.dist-info/WHEEL
scKinetics-0.2.2.dist-info/top_level.txt
scKinetics-0.2.2.dist-info/RECORD
